compactdenial.py
compactdenial-0.0.5.data/scripts/compactrcode.py
compactdenial-0.0.5.dist-info/LICENSE
compactdenial-0.0.5.dist-info/METADATA
compactdenial-0.0.5.dist-info/WHEEL
compactdenial-0.0.5.dist-info/top_level.txt
compactdenial-0.0.5.dist-info/RECORD
