Metadata-Version: 2.1
Name: compactdenial
Version: 0.0.5
Summary: DNS Compact Denial of Existence Library
Home-page: https://github.com/shuque/compactdenial
Author: Shumon Huque
Author-email: Shumon Huque <shuque@gmail.com>
Project-URL: Homepage, https://github.com/shuque/compactdenial
Project-URL: Issues, https://github.com/shuque/compactdenial/issues
Classifier: Programming Language :: Python :: 3
Classifier: License :: OSI Approved :: MIT License
Classifier: Operating System :: OS Independent
Requires-Python: >=3.8
License-File: LICENSE
Requires-Dist: dnspython
